{"items": [
    {
        "year": 1960,
        "coal": 356.145,
        "gas": 222202.08,
        "nuclear": 0,
        "crude-oil": 148943.52778,
        "renewable": 48103.65939
    },
    {
        "year": 1961,
        "coal": 275.38211,
        "gas": 215311.05,
        "nuclear": 0,
        "crude-oil": 160782.17154,
        "renewable": 51144.09932
    },
    {
        "year": 1962,
        "coal": 159.72074,
        "gas": 235476.99,
        "nuclear": 0,
        "crude-oil": 167167.20486,
        "renewable": 47637.43121
    },
    {
        "year": 1963,
        "coal": 134.54345,
        "gas": 252846,
        "nuclear": 0,
        "crude-oil": 173908.7732,
        "renewable": 41896.76435
    },
    {
        "year": 1964,
        "coal": 186.16507,
        "gas": 278852.054,
        "nuclear": 0,
        "crude-oil": 185296.31653,
        "renewable": 42731.66673
    },
    {
        "year": 1965,
        "coal": 163.23664,
        "gas": 277661.384,
        "nuclear": 0,
        "crude-oil": 180013.3062,
        "renewable": 46424.79616
    },
    {
        "year": 1966,
        "coal": 110.70274,
        "gas": 289632.343,
        "nuclear": 0,
        "crude-oil": 195734.71318,
        "renewable": 51697.18153
    },
    {
        "year": 1967,
        "coal": 104.01557,
        "gas": 295755.6572,
        "nuclear": 0,
        "crude-oil": 200062.67953,
        "renewable": 46123.79032
    },
    {
        "year": 1968,
        "coal": 132.11179,
        "gas": 321568.537,
        "nuclear": 0,
        "crude-oil": 219778.22487,
        "renewable": 64986.44209
    },
    {
        "year": 1969,
        "coal": 0,
        "gas": 349989.734,
        "nuclear": 0,
        "crude-oil": 236884.38732,
        "renewable": 64813.20196
    },
    {
        "year": 1970,
        "coal": 0,
        "gas": 383478.37328,
        "nuclear": 0,
        "crude-oil": 246344.70748,
        "renewable": 56932.64487
    },
    {
        "year": 1971,
        "coal": 50.52502,
        "gas": 334978.68042,
        "nuclear": 0,
        "crude-oil": 272571.65968,
        "renewable": 53579.16257
    },
    {
        "year": 1972,
        "coal": 50.2918,
        "gas": 317640.12852,
        "nuclear": 0,
        "crude-oil": 315378.24467,
        "renewable": 53916.8892
    },
    {
        "year": 1973,
        "coal": 2261.95624,
        "gas": 327475.38481,
        "nuclear": 0,
        "crude-oil": 357282.89314,
        "renewable": 81722.76698
    },
    {
        "year": 1974,
        "coal": 2665.34272,
        "gas": 290102.19541,
        "nuclear": 4024.18784,
        "crude-oil": 358916.68314,
        "renewable": 81338.55189
    },
    {
        "year": 1975,
        "coal": 861.92654,
        "gas": 257445.05984,
        "nuclear": 53675.666,
        "crude-oil": 345425.30284,
        "renewable": 71589.00795
    },
    {
        "year": 1976,
        "coal": 3578.21611,
        "gas": 248193.93473,
        "nuclear": 42614.42113,
        "crude-oil": 385230.15912,
        "renewable": 62299.52669
    },
    {
        "year": 1977,
        "coal": 5243.56883,
        "gas": 234378.8201,
        "nuclear": 54758.92195,
        "crude-oil": 431087.4599,
        "renewable": 69745.70669
    },
    {
        "year": 1978,
        "coal": 22833.18419,
        "gas": 220898.09952,
        "nuclear": 57113.34386,
        "crude-oil": 429030.53031,
        "renewable": 77087.91946
    },
    {
        "year": 1979,
        "coal": 31728.02619,
        "gas": 255009.65629,
        "nuclear": 42139.09937,
        "crude-oil": 369459.73604,
        "renewable": 80772.97216
    },
    {
        "year": 1980,
        "coal": 36648.21507,
        "gas": 273994.13341,
        "nuclear": 85437.62993,
        "crude-oil": 311342.53984,
        "renewable": 69996.25945
    },
    {
        "year": 1981,
        "coal": 101934.80035,
        "gas": 265051.37959,
        "nuclear": 100092.97036,
        "crude-oil": 299254.36897,
        "renewable": 68248.44216
    },
    {
        "year": 1982,
        "coal": 125192.57399,
        "gas": 227395.381,
        "nuclear": 82851.98404,
        "crude-oil": 289080.64445,
        "renewable": 77652.01863
    },
    {
        "year": 1983,
        "coal": 177458.2024,
        "gas": 211725.81596,
        "nuclear": 83380.2734,
        "crude-oil": 290824.86141,
        "renewable": 95412.0244
    },
    {
        "year": 1984,
        "coal": 163878.95888,
        "gas": 214432.10465,
        "nuclear": 117188.17302,
        "crude-oil": 270466.59483,
        "renewable": 91645.98167
    },
    {
        "year": 1985,
        "coal": 219791.05271,
        "gas": 199349.59494,
        "nuclear": 105042.43446,
        "crude-oil": 270554.79165,
        "renewable": 109250.67346
    },
    {
        "year": 1986,
        "coal": 224546.61021,
        "gas": 202981.8826,
        "nuclear": 93900.21958,
        "crude-oil": 265040.34837,
        "renewable": 91233.98286
    },
    {
        "year": 1987,
        "coal": 211010.86263,
        "gas": 172339.62687,
        "nuclear": 118719.70292,
        "crude-oil": 264927.16191,
        "renewable": 86687.97995
    },
    {
        "year": 1988,
        "coal": 218821.2514,
        "gas": 218786.69864,
        "nuclear": 94309.26404,
        "crude-oil": 278194.48923,
        "renewable": 92546.08188
    },
    {
        "year": 1989,
        "coal": 203343.1629,
        "gas": 251139.09146,
        "nuclear": 93598.61309,
        "crude-oil": 277023.15955,
        "renewable": 119780.43424
    },
    {
        "year": 1990,
        "coal": 212706.56139,
        "gas": 234465.08045,
        "nuclear": 119386.68485,
        "crude-oil": 267879.69413,
        "renewable": 110528.88382
    },
    {
        "year": 1991,
        "coal": 215944.62898,
        "gas": 212679.85753,
        "nuclear": 132746.23781,
        "crude-oil": 264550.48567,
        "renewable": 110168.61889
    },
    {
        "year": 1992,
        "coal": 220705.97094,
        "gas": 226597.73693,
        "nuclear": 118590.99633,
        "crude-oil": 274476.24119,
        "renewable": 112836.12955
    },
    {
        "year": 1993,
        "coal": 200449.99364,
        "gas": 232681.61467,
        "nuclear": 142031.6847,
        "crude-oil": 288412.81121,
        "renewable": 133831.64371
    },
    {
        "year": 1994,
        "coal": 222168.80612,
        "gas": 247187.39102,
        "nuclear": 145530.52285,
        "crude-oil": 300793.11729,
        "renewable": 119639.98414
    },
    {
        "year": 1995,
        "coal": 237334.00674,
        "gas": 271956.18432,
        "nuclear": 122485.86734,
        "crude-oil": 310062.01008,
        "renewable": 117539.66959
    },
    {
        "year": 1996,
        "coal": 260060.15641,
        "gas": 274990.55528,
        "nuclear": 140285.11551,
        "crude-oil": 337188.59977,
        "renewable": 118052.45424
    },
    {
        "year": 1997,
        "coal": 246786.37421,
        "gas": 264019.34283,
        "nuclear": 149100.39956,
        "crude-oil": 351687.90598,
        "renewable": 124083.47596
    },
    {
        "year": 1998,
        "coal": 254658.30749,
        "gas": 272887.89087,
        "nuclear": 137403.27073,
        "crude-oil": 352346.21229,
        "renewable": 114968.04285
    },
    {
        "year": 1999,
        "coal": 267022.4263,
        "gas": 257666.32966,
        "nuclear": 135009.2975,
        "crude-oil": 380652.96506,
        "renewable": 110921.4919
    },
    {
        "year": 2000,
        "coal": 267578.51006,
        "gas": 256114.189,
        "nuclear": 121516.33019,
        "crude-oil": 388112.91643,
        "renewable": 108731.18512
    },
    {
        "year": 2001,
        "coal": 273982.37882,
        "gas": 231589.60743,
        "nuclear": 154355.77953,
        "crude-oil": 375402.57154,
        "renewable": 94047.40973
    },
    {
        "year": 2002,
        "coal": 255241.63179,
        "gas": 247898.39316,
        "nuclear": 152023.86673,
        "crude-oil": 378600.00836,
        "renewable": 108661.86977
    },
    {
        "year": 2003,
        "coal": 253652.76144,
        "gas": 254570.85273,
        "nuclear": 153078.40414,
        "crude-oil": 377268.18949,
        "renewable": 108251.72002
    },
    {
        "year": 2004,
        "coal": 270210.48598,
        "gas": 217920.97772,
        "nuclear": 161095.59638,
        "crude-oil": 388326.92669,
        "renewable": 112967.60789
    },
    {
        "year": 2005,
        "coal": 247169.29691,
        "gas": 216599.94074,
        "nuclear": 142864.36296,
        "crude-oil": 383741.73129,
        "renewable": 112559.09413
    },
    {
        "year": 2006,
        "coal": 256907.33345,
        "gas": 240884.77446,
        "nuclear": 158967.17357,
        "crude-oil": 372596.27099,
        "renewable": 100228.01312
    },
    {
        "year": 2007,
        "coal": 275037.24849,
        "gas": 228024.61879,
        "nuclear": 162371.77947,
        "crude-oil": 375340.85982,
        "renewable": 121161.52904
    },
    {
        "year": 2008,
        "coal": 278849.04345,
        "gas": 238423.95168,
        "nuclear": 148099.05522,
        "crude-oil": 366878.34691,
        "renewable": 125607.80806
    },
    {
        "year": 2009,
        "coal": 264083.32512,
        "gas": 248097.5165,
        "nuclear": 158677.84436,
        "crude-oil": 349136.82362,
        "renewable": 126536.95014
    }
]}